oem2orm/__init__.py
oem2orm/main.py
oem2orm/oep_compliance.py
oem2orm/oep_oedialect_oem2orm.py
oem2orm/postgresql_types.py
oem2orm/settings.py
oem2orm-0.4.1.dist-info/LICENSE
oem2orm-0.4.1.dist-info/METADATA
oem2orm-0.4.1.dist-info/WHEEL
oem2orm-0.4.1.dist-info/entry_points.txt
oem2orm-0.4.1.dist-info/top_level.txt
oem2orm-0.4.1.dist-info/RECORD
