Metadata-Version: 2.1
Name: oem2orm
Version: 0.4.1
Summary: SQLAlchemy module to generate ORM, read from data model (oedatamodel) in open-energy-metadata JSON format
Home-page: https://github.com/OpenEnergyPlatform/oem2orm
Author: henhuy, jh-RLI
Author-email: Hendrik.Huyskens@rl-institut.de
Project-URL: Bug Reports, https://github.com/OpenEnergyPlatform/oem2orm/issues
Project-URL: Source, https://github.com/OpenEnergyPlatform/oem2orm/tree/develop/oem2orm
Classifier: Development Status :: 3 - Alpha
Classifier: Intended Audience :: Developers
Classifier: Programming Language :: Python :: 3
Classifier: License :: OSI Approved :: GNU Affero General Public License v3
Classifier: Operating System :: OS Independent
Requires-Python: >=3.6
License-File: LICENSE
Requires-Dist: sqlalchemy ==1.3.16
Requires-Dist: oedialect ==0.1.1
Requires-Dist: requests
Requires-Dist: jmespath
Requires-Dist: omi
Requires-Dist: click
